pyonmttok/__init__.py
pyonmttok/_ext.cpython-310-darwin.so
pyonmttok/version.py
pyonmttok-1.38.1.dist-info/METADATA
pyonmttok-1.38.1.dist-info/WHEEL
pyonmttok-1.38.1.dist-info/top_level.txt
pyonmttok-1.38.1.dist-info/RECORD
