Metadata-Version: 2.4
Name: pyonmttok
Version: 1.38.1
Summary: Fast and customizable text tokenization library with BPE and SentencePiece support
Home-page: https://opennmt.net
Author: OpenNMT
License: MIT
Project-URL: Forum, https://forum.opennmt.net/
Project-URL: Source, https://github.com/OpenNMT/Tokenizer/
Keywords: tokenization opennmt unicode bpe sentencepiece subword
Classifier: Development Status :: 5 - Production/Stable
Classifier: Intended Audience :: Developers
Classifier: Intended Audience :: Science/Research
Classifier: License :: OSI Approved :: MIT License
Classifier: Programming Language :: Python :: 3
Classifier: Programming Language :: Python :: 3 :: Only
Classifier: Programming Language :: Python :: 3.10
Classifier: Programming Language :: Python :: 3.11
Classifier: Programming Language :: Python :: 3.12
Classifier: Topic :: Text Processing :: Linguistic
Classifier: Topic :: Software Development :: Libraries :: Python Modules
Requires-Python: >=3.10
Dynamic: author
Dynamic: classifier
Dynamic: description
Dynamic: description-content-type
Dynamic: home-page
Dynamic: keywords
Dynamic: license
Dynamic: project-url
Dynamic: requires-python
Dynamic: summary
